<?xml version="1.0" encoding="UTF-8"?>
<mets xmlns:xsi="http://www.w3.org/2001/XMLSchema-instance" xsi:schemaLocation="http://www.loc.gov/METS/ http://www.loc.gov/standards/mets/mets.xsd http://www.loc.gov/mix/ http://schema.ccs-gmbh.com/docworks/version20/mix_jp2.xsd http://www.loc.gov/mods/v3 http://www.loc.gov/standards/mods/v3/mods-3-3.xsd" xmlns="http://www.loc.gov/METS/" xmlns:mix="http://www.loc.gov/mix/" xmlns:xlink="http://www.w3.org/1999/xlink" xmlns:local="http://diglib.princeton.edu" xmlns:mods="http://www.loc.gov/mods/v3" TYPE="Magazine" OBJID="urn:PUL:periodicals:bluemountain:bmtnabd_1894-10-20_01">
	<metsHdr>
		<agent ROLE="CREATOR" TYPE="ORGANIZATION">
			<name>Princeton University Library, Digital Initiatives</name>
			<note>docWORKS-ID: 880654</note>
		</agent>
		<metsDocumentID TYPE="URN">urn:PUL:bluemountain:td:bmtnabd_1894-10-20_01</metsDocumentID>
	</metsHdr>
	<dmdSec ID="dmd1">
		<mdWrap MDTYPE="MODS">
			<xmlData>
				<mods xmlns="http://www.loc.gov/mods/v3">
					<recordInfo>
						<recordIdentifier>urn:PUL:BlueMountain:dmd:bmtnabd_1894-10-20_01</recordIdentifier>
					</recordInfo>
					<identifier type="bmtn">urn:PUL:BlueMountain:bmtnabd_1894-10-20_01</identifier>
					<typeOfResource>text</typeOfResource>
					<genre>Periodicals-Issue</genre>
					<titleInfo>
						<title>Dalibor</title>
						<subTitle>Hudební listy.</subTitle>
					</titleInfo>
					<part type="issue">
						<detail type="number">
							<number>42</number>
							<caption>Číslo 42.</caption>
						</detail>
						<detail type="volume">
							<number>16</number>
							<caption>Ročnik XVI.</caption>
						</detail>
					</part>
					<originInfo>
						<dateIssued>20. října 1894.</dateIssued>
						<dateIssued keyDate="yes">1894-10-20</dateIssued>
					</originInfo>
					<relatedItem xmlns:xlink="http://www.w3.org/1999/xlink" type="host" xlink:type="simple" xlink:href="urn:PUL:bluemountain:bmtnabd">
						<recordInfo>
							<recordIdentifier>urn:PUL:bluemountain:dmd:bmtnabd</recordIdentifier>
						</recordInfo>
					</relatedItem>
					<relatedItem type="constituent" ID="c001">
						<titleInfo lang="cze">
							<title>HUDEBNÍ LISTY.</title>
						</titleInfo>
						<typeOfResource>text</typeOfResource>
						<language>
							<languageTerm authority="iso639-2b">cze</languageTerm>
						</language>
						<part>
							<extent unit="page">
								<start>1</start>
							</extent>
						</part>
						<genre type="CCS">TextContent</genre>
					</relatedItem>
					<relatedItem type="constituent" ID="c002">
						<titleInfo lang="cze">
							<title>OBSAH:</title>
						</titleInfo>
						<typeOfResource>text</typeOfResource>
						<language>
							<languageTerm authority="iso639-2b">cze</languageTerm>
						</language>
						<part>
							<extent unit="page">
								<start>1</start>
							</extent>
						</part>
						<genre type="CCS">TextContent</genre>
					</relatedItem>
					<relatedItem type="constituent" ID="c003">
						<titleInfo lang="cze">
							<title>NÁRODNÍ DIVADLO V PRAZE.</title>
						</titleInfo>
						<typeOfResource>text</typeOfResource>
						<language>
							<languageTerm authority="iso639-2b">cze</languageTerm>
						</language>
						<part>
							<extent unit="page">
								<list>1-3</list>
							</extent>
						</part>
						<genre type="CCS">TextContent</genre>
					</relatedItem>
					<relatedItem type="constituent" ID="c004">
						<titleInfo lang="cze">
							<title>Z KONCERTNÍ SÍNĚ.</title>
						</titleInfo>
						<typeOfResource>text</typeOfResource>
						<language>
							<languageTerm authority="iso639-2b">cze</languageTerm>
						</language>
						<part>
							<extent unit="page">
								<list>3-5</list>
							</extent>
						</part>
						<genre type="CCS">TextContent</genre>
					</relatedItem>
					<relatedItem type="constituent" ID="c005">
						<titleInfo lang="cze">
							<title>LITERATURA,</title>
						</titleInfo>
						<typeOfResource>text</typeOfResource>
						<language>
							<languageTerm authority="iso639-2b">cze</languageTerm>
						</language>
						<part>
							<extent unit="page">
								<start>5</start>
							</extent>
						</part>
						<genre type="CCS">TextContent</genre>
					</relatedItem>
					<relatedItem type="constituent" ID="c006">
						<titleInfo lang="cze">
							<title>Činnost našich spolkův a ruch náš hudební.</title>
						</titleInfo>
						<typeOfResource>text</typeOfResource>
						<language>
							<languageTerm authority="iso639-2b">cze</languageTerm>
						</language>
						<part>
							<extent unit="page">
								<list>5-8</list>
							</extent>
						</part>
						<genre type="CCS">TextContent</genre>
					</relatedItem>
					<relatedItem type="constituent" ID="c007">
						<titleInfo lang="cze">
							<title>ÚMRTÍ.</title>
						</titleInfo>
						<typeOfResource>text</typeOfResource>
						<language>
							<languageTerm authority="iso639-2b">cze</languageTerm>
						</language>
						<part>
							<extent unit="page">
								<start>8</start>
							</extent>
						</part>
						<genre type="CCS">TextContent</genre>
					</relatedItem>
					<relatedItem type="constituent" ID="c008">
						<titleInfo lang="cze">
							<title>RŮZNÉ ZPRÁVY.</title>
						</titleInfo>
						<typeOfResource>text</typeOfResource>
						<language>
							<languageTerm authority="iso639-2b">cze</languageTerm>
						</language>
						<part>
							<extent unit="page">
								<list>8-11</list>
							</extent>
						</part>
						<genre type="CCS">TextContent</genre>
					</relatedItem>
					<relatedItem type="constituent" ID="c009">
						<titleInfo lang="cze">
							<title>SMĚS.</title>
						</titleInfo>
						<typeOfResource>text</typeOfResource>
						<language>
							<languageTerm authority="iso639-2b">cze</languageTerm>
						</language>
						<part>
							<extent unit="page">
								<start>11</start>
							</extent>
						</part>
						<genre type="CCS">TextContent</genre>
					</relatedItem>
					<relatedItem type="constituent" ID="c010">
						<titleInfo lang="cze">
							<title>Listárna redakce.</title>
						</titleInfo>
						<typeOfResource>text</typeOfResource>
						<language>
							<languageTerm authority="iso639-2b">cze</languageTerm>
						</language>
						<part>
							<extent unit="page">
								<start>11</start>
							</extent>
						</part>
						<genre type="CCS">TextContent</genre>
					</relatedItem>
					<relatedItem type="constituent" ID="c011">
						<titleInfo>
							<title>[Advertisement]</title>
						</titleInfo>
						<genre>advertisement</genre>
						<typeOfResource>text</typeOfResource>
						<part>
							<extent unit="page">
								<start>11</start>
							</extent>
						</part>
						<genre type="CCS">SponsoredAdvertisement</genre>
					</relatedItem>
					<relatedItem type="constituent" ID="c012">
						<titleInfo>
							<title>[Advertisement]</title>
						</titleInfo>
						<genre>advertisement</genre>
						<typeOfResource>text</typeOfResource>
						<part>
							<extent unit="page">
								<start>12</start>
							</extent>
						</part>
						<genre type="CCS">SponsoredAdvertisement</genre>
					</relatedItem>
					<relatedItem type="constituent" ID="c013">
						<titleInfo>
							<title>[Advertisement]</title>
						</titleInfo>
						<genre>advertisement</genre>
						<typeOfResource>text</typeOfResource>
						<part>
							<extent unit="page">
								<start>12</start>
							</extent>
						</part>
						<genre type="CCS">SponsoredAdvertisement</genre>
					</relatedItem>
				</mods>
			</xmlData>
		</mdWrap>
	</dmdSec>
	<amdSec>
		<techMD ID="techmd1">
			<mdWrap MDTYPE="NISOIMG">
				<xmlData>
					<mix:mix>
						<mix:BasicImageParameters>
							<mix:Format>
								<mix:MIMEType>image/jp2</mix:MIMEType>
								<mix:ByteOrder>little-endian</mix:ByteOrder>
								<mix:Compression>
									<mix:CompressionScheme>34712</mix:CompressionScheme>
								</mix:Compression>
								<mix:PhotometricInterpretation>
									<mix:ColorSpace>2</mix:ColorSpace>
								</mix:PhotometricInterpretation>
							</mix:Format>
							<mix:File>
								<mix:ImageIdentifier imageIdentifierLocation="//fileserver3/OUT6/PUL-DaliborMusicJournal/Dalibor/bmtnabd/issues/1894/10/20_01/alto">bmtnabd_1894-10-20_01_0001.jp2</mix:ImageIdentifier>
								<mix:FileSize>4514070</mix:FileSize>
								<mix:Orientation>1</mix:Orientation>
								<mix:DisplayOrientation>1</mix:DisplayOrientation>
							</mix:File>
						</mix:BasicImageParameters>
						<mix:ImageCreation>
							<mix:SourceType>METAe_Serial</mix:SourceType>
							<mix:SourceID/>
							<mix:ImageProducer/>
							<mix:Host>
								<mix:HostComputer>DWP4</mix:HostComputer>
								<mix:OperatingSystem>windows</mix:OperatingSystem>
								<mix:OSVersion>7 SP1</mix:OSVersion>
							</mix:Host>
							<mix:DeviceSource/>
							<mix:ScanningSystemCapture>
								<mix:ScanningSystemHardware>
									<mix:ScannerManufacturer/>
									<mix:ScannerModel>
										<mix:ScannerModelName/>
										<mix:ScannerModelNumber/>
										<mix:ScannerModelSerialNo/>
									</mix:ScannerModel>
								</mix:ScanningSystemHardware>
								<mix:ScanningSystemSoftware>
									<mix:ScanningSoftware>CCS docWorks</mix:ScanningSoftware>
									<mix:ScanningSoftwareVersionNo/>
								</mix:ScanningSystemSoftware>
								<mix:ScannerCaptureSettings>
									<mix:PixelSize>0.0423333</mix:PixelSize>
									<mix:PhysScanResolution>
										<mix:XphysScanResolution>600</mix:XphysScanResolution>
										<mix:YphysScanResolution>600</mix:YphysScanResolution>
									</mix:PhysScanResolution>
								</mix:ScannerCaptureSettings>
							</mix:ScanningSystemCapture>
						</mix:ImageCreation>
						<mix:ImagingPerformanceAssessment>
							<mix:SpatialMetrics>
								<mix:ImageWidth>5304</mix:ImageWidth>
								<mix:ImageLength>6807</mix:ImageLength>
							</mix:SpatialMetrics>
							<mix:Energetics>
								<mix:BitsPerSample>8,8,8</mix:BitsPerSample>
								<mix:SamplesPerPixel>3</mix:SamplesPerPixel>
							</mix:Energetics>
						</mix:ImagingPerformanceAssessment>
						<mix:ChangeHistory>
							<mix:ImageProcessing>
								<mix:SourceData>./PUL-DaliborMusicJournal/1894/10/20_01/00000329.tif</mix:SourceData>
							</mix:ImageProcessing>
						</mix:ChangeHistory>
					</mix:mix>
				</xmlData>
			</mdWrap>
		</techMD>
		<techMD ID="techmd2">
			<mdWrap MDTYPE="NISOIMG">
				<xmlData>
					<mix:mix>
						<mix:BasicImageParameters>
							<mix:Format>
								<mix:MIMEType>image/jp2</mix:MIMEType>
								<mix:ByteOrder>little-endian</mix:ByteOrder>
								<mix:Compression>
									<mix:CompressionScheme>34712</mix:CompressionScheme>
								</mix:Compression>
								<mix:PhotometricInterpretation>
									<mix:ColorSpace>2</mix:ColorSpace>
								</mix:PhotometricInterpretation>
							</mix:Format>
							<mix:File>
								<mix:ImageIdentifier imageIdentifierLocation="//fileserver3/OUT6/PUL-DaliborMusicJournal/Dalibor/bmtnabd/issues/1894/10/20_01/alto">bmtnabd_1894-10-20_01_0002.jp2</mix:ImageIdentifier>
								<mix:FileSize>4512558</mix:FileSize>
								<mix:Orientation>1</mix:Orientation>
								<mix:DisplayOrientation>1</mix:DisplayOrientation>
							</mix:File>
						</mix:BasicImageParameters>
						<mix:ImageCreation>
							<mix:SourceType>METAe_Serial</mix:SourceType>
							<mix:SourceID/>
							<mix:ImageProducer/>
							<mix:Host>
								<mix:HostComputer>DWP4</mix:HostComputer>
								<mix:OperatingSystem>windows</mix:OperatingSystem>
								<mix:OSVersion>7 SP1</mix:OSVersion>
							</mix:Host>
							<mix:DeviceSource/>
							<mix:ScanningSystemCapture>
								<mix:ScanningSystemHardware>
									<mix:ScannerManufacturer/>
									<mix:ScannerModel>
										<mix:ScannerModelName/>
										<mix:ScannerModelNumber/>
										<mix:ScannerModelSerialNo/>
									</mix:ScannerModel>
								</mix:ScanningSystemHardware>
								<mix:ScanningSystemSoftware>
									<mix:ScanningSoftware>CCS docWorks</mix:ScanningSoftware>
									<mix:ScanningSoftwareVersionNo/>
								</mix:ScanningSystemSoftware>
								<mix:ScannerCaptureSettings>
									<mix:PixelSize>0.0423333</mix:PixelSize>
									<mix:PhysScanResolution>
										<mix:XphysScanResolution>600</mix:XphysScanResolution>
										<mix:YphysScanResolution>600</mix:YphysScanResolution>
									</mix:PhysScanResolution>
								</mix:ScannerCaptureSettings>
							</mix:ScanningSystemCapture>
						</mix:ImageCreation>
						<mix:ImagingPerformanceAssessment>
							<mix:SpatialMetrics>
								<mix:ImageWidth>5303</mix:ImageWidth>
								<mix:ImageLength>6806</mix:ImageLength>
							</mix:SpatialMetrics>
							<mix:Energetics>
								<mix:BitsPerSample>8,8,8</mix:BitsPerSample>
								<mix:SamplesPerPixel>3</mix:SamplesPerPixel>
							</mix:Energetics>
						</mix:ImagingPerformanceAssessment>
						<mix:ChangeHistory>
							<mix:ImageProcessing>
								<mix:SourceData>./PUL-DaliborMusicJournal/1894/10/20_01/00000330.tif</mix:SourceData>
							</mix:ImageProcessing>
						</mix:ChangeHistory>
					</mix:mix>
				</xmlData>
			</mdWrap>
		</techMD>
		<techMD ID="techmd3">
			<mdWrap MDTYPE="NISOIMG">
				<xmlData>
					<mix:mix>
						<mix:BasicImageParameters>
							<mix:Format>
								<mix:MIMEType>image/jp2</mix:MIMEType>
								<mix:ByteOrder>little-endian</mix:ByteOrder>
								<mix:Compression>
									<mix:CompressionScheme>34712</mix:CompressionScheme>
								</mix:Compression>
								<mix:PhotometricInterpretation>
									<mix:ColorSpace>2</mix:ColorSpace>
								</mix:PhotometricInterpretation>
							</mix:Format>
							<mix:File>
								<mix:ImageIdentifier imageIdentifierLocation="//fileserver3/OUT6/PUL-DaliborMusicJournal/Dalibor/bmtnabd/issues/1894/10/20_01/alto">bmtnabd_1894-10-20_01_0003.jp2</mix:ImageIdentifier>
								<mix:FileSize>4508799</mix:FileSize>
								<mix:Orientation>1</mix:Orientation>
								<mix:DisplayOrientation>1</mix:DisplayOrientation>
							</mix:File>
						</mix:BasicImageParameters>
						<mix:ImageCreation>
							<mix:SourceType>METAe_Serial</mix:SourceType>
							<mix:SourceID/>
							<mix:ImageProducer/>
							<mix:Host>
								<mix:HostComputer>DWP4</mix:HostComputer>
								<mix:OperatingSystem>windows</mix:OperatingSystem>
								<mix:OSVersion>7 SP1</mix:OSVersion>
							</mix:Host>
							<mix:DeviceSource/>
							<mix:ScanningSystemCapture>
								<mix:ScanningSystemHardware>
									<mix:ScannerManufacturer/>
									<mix:ScannerModel>
										<mix:ScannerModelName/>
										<mix:ScannerModelNumber/>
										<mix:ScannerModelSerialNo/>
									</mix:ScannerModel>
								</mix:ScanningSystemHardware>
								<mix:ScanningSystemSoftware>
									<mix:ScanningSoftware>CCS docWorks</mix:ScanningSoftware>
									<mix:ScanningSoftwareVersionNo/>
								</mix:ScanningSystemSoftware>
								<mix:ScannerCaptureSettings>
									<mix:PixelSize>0.0423333</mix:PixelSize>
									<mix:PhysScanResolution>
										<mix:XphysScanResolution>600</mix:XphysScanResolution>
										<mix:YphysScanResolution>600</mix:YphysScanResolution>
									</mix:PhysScanResolution>
								</mix:ScannerCaptureSettings>
							</mix:ScanningSystemCapture>
						</mix:ImageCreation>
						<mix:ImagingPerformanceAssessment>
							<mix:SpatialMetrics>
								<mix:ImageWidth>5304</mix:ImageWidth>
								<mix:ImageLength>6806</mix:ImageLength>
							</mix:SpatialMetrics>
							<mix:Energetics>
								<mix:BitsPerSample>8,8,8</mix:BitsPerSample>
								<mix:SamplesPerPixel>3</mix:SamplesPerPixel>
							</mix:Energetics>
						</mix:ImagingPerformanceAssessment>
						<mix:ChangeHistory>
							<mix:ImageProcessing>
								<mix:SourceData>./PUL-DaliborMusicJournal/1894/10/20_01/00000331.tif</mix:SourceData>
							</mix:ImageProcessing>
						</mix:ChangeHistory>
					</mix:mix>
				</xmlData>
			</mdWrap>
		</techMD>
		<techMD ID="techmd4">
			<mdWrap MDTYPE="NISOIMG">
				<xmlData>
					<mix:mix>
						<mix:BasicImageParameters>
							<mix:Format>
								<mix:MIMEType>image/jp2</mix:MIMEType>
								<mix:ByteOrder>little-endian</mix:ByteOrder>
								<mix:Compression>
									<mix:CompressionScheme>34712</mix:CompressionScheme>
								</mix:Compression>
								<mix:PhotometricInterpretation>
									<mix:ColorSpace>2</mix:ColorSpace>
								</mix:PhotometricInterpretation>
							</mix:Format>
							<mix:File>
								<mix:ImageIdentifier imageIdentifierLocation="//fileserver3/OUT6/PUL-DaliborMusicJournal/Dalibor/bmtnabd/issues/1894/10/20_01/alto">bmtnabd_1894-10-20_01_0004.jp2</mix:ImageIdentifier>
								<mix:FileSize>4521717</mix:FileSize>
								<mix:Orientation>1</mix:Orientation>
								<mix:DisplayOrientation>1</mix:DisplayOrientation>
							</mix:File>
						</mix:BasicImageParameters>
						<mix:ImageCreation>
							<mix:SourceType>METAe_Serial</mix:SourceType>
							<mix:SourceID/>
							<mix:ImageProducer/>
							<mix:Host>
								<mix:HostComputer>DWP4</mix:HostComputer>
								<mix:OperatingSystem>windows</mix:OperatingSystem>
								<mix:OSVersion>7 SP1</mix:OSVersion>
							</mix:Host>
							<mix:DeviceSource/>
							<mix:ScanningSystemCapture>
								<mix:ScanningSystemHardware>
									<mix:ScannerManufacturer/>
									<mix:ScannerModel>
										<mix:ScannerModelName/>
										<mix:ScannerModelNumber/>
										<mix:ScannerModelSerialNo/>
									</mix:ScannerModel>
								</mix:ScanningSystemHardware>
								<mix:ScanningSystemSoftware>
									<mix:ScanningSoftware>CCS docWorks</mix:ScanningSoftware>
									<mix:ScanningSoftwareVersionNo/>
								</mix:ScanningSystemSoftware>
								<mix:ScannerCaptureSettings>
									<mix:PixelSize>0.0423333</mix:PixelSize>
									<mix:PhysScanResolution>
										<mix:XphysScanResolution>600</mix:XphysScanResolution>
										<mix:YphysScanResolution>600</mix:YphysScanResolution>
									</mix:PhysScanResolution>
								</mix:ScannerCaptureSettings>
							</mix:ScanningSystemCapture>
						</mix:ImageCreation>
						<mix:ImagingPerformanceAssessment>
							<mix:SpatialMetrics>
								<mix:ImageWidth>5303</mix:ImageWidth>
								<mix:ImageLength>6820</mix:ImageLength>
							</mix:SpatialMetrics>
							<mix:Energetics>
								<mix:BitsPerSample>8,8,8</mix:BitsPerSample>
								<mix:SamplesPerPixel>3</mix:SamplesPerPixel>
							</mix:Energetics>
						</mix:ImagingPerformanceAssessment>
						<mix:ChangeHistory>
							<mix:ImageProcessing>
								<mix:SourceData>./PUL-DaliborMusicJournal/1894/10/20_01/00000332.tif</mix:SourceData>
							</mix:ImageProcessing>
						</mix:ChangeHistory>
					</mix:mix>
				</xmlData>
			</mdWrap>
		</techMD>
		<techMD ID="techmd5">
			<mdWrap MDTYPE="NISOIMG">
				<xmlData>
					<mix:mix>
						<mix:BasicImageParameters>
							<mix:Format>
								<mix:MIMEType>image/jp2</mix:MIMEType>
								<mix:ByteOrder>little-endian</mix:ByteOrder>
								<mix:Compression>
									<mix:CompressionScheme>34712</mix:CompressionScheme>
								</mix:Compression>
								<mix:PhotometricInterpretation>
									<mix:ColorSpace>2</mix:ColorSpace>
								</mix:PhotometricInterpretation>
							</mix:Format>
							<mix:File>
								<mix:ImageIdentifier imageIdentifierLocation="//fileserver3/OUT6/PUL-DaliborMusicJournal/Dalibor/bmtnabd/issues/1894/10/20_01/alto">bmtnabd_1894-10-20_01_0005.jp2</mix:ImageIdentifier>
								<mix:FileSize>4522608</mix:FileSize>
								<mix:Orientation>1</mix:Orientation>
								<mix:DisplayOrientation>1</mix:DisplayOrientation>
							</mix:File>
						</mix:BasicImageParameters>
						<mix:ImageCreation>
							<mix:SourceType>METAe_Serial</mix:SourceType>
							<mix:SourceID/>
							<mix:ImageProducer/>
							<mix:Host>
								<mix:HostComputer>DWP4</mix:HostComputer>
								<mix:OperatingSystem>windows</mix:OperatingSystem>
								<mix:OSVersion>7 SP1</mix:OSVersion>
							</mix:Host>
							<mix:DeviceSource/>
							<mix:ScanningSystemCapture>
								<mix:ScanningSystemHardware>
									<mix:ScannerManufacturer/>
									<mix:ScannerModel>
										<mix:ScannerModelName/>
										<mix:ScannerModelNumber/>
										<mix:ScannerModelSerialNo/>
									</mix:ScannerModel>
								</mix:ScanningSystemHardware>
								<mix:ScanningSystemSoftware>
									<mix:ScanningSoftware>CCS docWorks</mix:ScanningSoftware>
									<mix:ScanningSoftwareVersionNo/>
								</mix:ScanningSystemSoftware>
								<mix:ScannerCaptureSettings>
									<mix:PixelSize>0.0423333</mix:PixelSize>
									<mix:PhysScanResolution>
										<mix:XphysScanResolution>600</mix:XphysScanResolution>
										<mix:YphysScanResolution>600</mix:YphysScanResolution>
									</mix:PhysScanResolution>
								</mix:ScannerCaptureSettings>
							</mix:ScanningSystemCapture>
						</mix:ImageCreation>
						<mix:ImagingPerformanceAssessment>
							<mix:SpatialMetrics>
								<mix:ImageWidth>5304</mix:ImageWidth>
								<mix:ImageLength>6820</mix:ImageLength>
							</mix:SpatialMetrics>
							<mix:Energetics>
								<mix:BitsPerSample>8,8,8</mix:BitsPerSample>
								<mix:SamplesPerPixel>3</mix:SamplesPerPixel>
							</mix:Energetics>
						</mix:ImagingPerformanceAssessment>
						<mix:ChangeHistory>
							<mix:ImageProcessing>
								<mix:SourceData>./PUL-DaliborMusicJournal/1894/10/20_01/00000333.tif</mix:SourceData>
							</mix:ImageProcessing>
						</mix:ChangeHistory>
					</mix:mix>
				</xmlData>
			</mdWrap>
		</techMD>
		<techMD ID="techmd6">
			<mdWrap MDTYPE="NISOIMG">
				<xmlData>
					<mix:mix>
						<mix:BasicImageParameters>
							<mix:Format>
								<mix:MIMEType>image/jp2</mix:MIMEType>
								<mix:ByteOrder>little-endian</mix:ByteOrder>
								<mix:Compression>
									<mix:CompressionScheme>34712</mix:CompressionScheme>
								</mix:Compression>
								<mix:PhotometricInterpretation>
									<mix:ColorSpace>2</mix:ColorSpace>
								</mix:PhotometricInterpretation>
							</mix:Format>
							<mix:File>
								<mix:ImageIdentifier imageIdentifierLocation="//fileserver3/OUT6/PUL-DaliborMusicJournal/Dalibor/bmtnabd/issues/1894/10/20_01/alto">bmtnabd_1894-10-20_01_0006.jp2</mix:ImageIdentifier>
								<mix:FileSize>4513870</mix:FileSize>
								<mix:Orientation>1</mix:Orientation>
								<mix:DisplayOrientation>1</mix:DisplayOrientation>
							</mix:File>
						</mix:BasicImageParameters>
						<mix:ImageCreation>
							<mix:SourceType>METAe_Serial</mix:SourceType>
							<mix:SourceID/>
							<mix:ImageProducer/>
							<mix:Host>
								<mix:HostComputer>DWP4</mix:HostComputer>
								<mix:OperatingSystem>windows</mix:OperatingSystem>
								<mix:OSVersion>7 SP1</mix:OSVersion>
							</mix:Host>
							<mix:DeviceSource/>
							<mix:ScanningSystemCapture>
								<mix:ScanningSystemHardware>
									<mix:ScannerManufacturer/>
									<mix:ScannerModel>
										<mix:ScannerModelName/>
										<mix:ScannerModelNumber/>
										<mix:ScannerModelSerialNo/>
									</mix:ScannerModel>
								</mix:ScanningSystemHardware>
								<mix:ScanningSystemSoftware>
									<mix:ScanningSoftware>CCS docWorks</mix:ScanningSoftware>
									<mix:ScanningSoftwareVersionNo/>
								</mix:ScanningSystemSoftware>
								<mix:ScannerCaptureSettings>
									<mix:PixelSize>0.0423333</mix:PixelSize>
									<mix:PhysScanResolution>
										<mix:XphysScanResolution>600</mix:XphysScanResolution>
										<mix:YphysScanResolution>600</mix:YphysScanResolution>
									</mix:PhysScanResolution>
								</mix:ScannerCaptureSettings>
							</mix:ScanningSystemCapture>
						</mix:ImageCreation>
						<mix:ImagingPerformanceAssessment>
							<mix:SpatialMetrics>
								<mix:ImageWidth>5303</mix:ImageWidth>
								<mix:ImageLength>6808</mix:ImageLength>
							</mix:SpatialMetrics>
							<mix:Energetics>
								<mix:BitsPerSample>8,8,8</mix:BitsPerSample>
								<mix:SamplesPerPixel>3</mix:SamplesPerPixel>
							</mix:Energetics>
						</mix:ImagingPerformanceAssessment>
						<mix:ChangeHistory>
							<mix:ImageProcessing>
								<mix:SourceData>./PUL-DaliborMusicJournal/1894/10/20_01/00000334.tif</mix:SourceData>
							</mix:ImageProcessing>
						</mix:ChangeHistory>
					</mix:mix>
				</xmlData>
			</mdWrap>
		</techMD>
		<techMD ID="techmd7">
			<mdWrap MDTYPE="NISOIMG">
				<xmlData>
					<mix:mix>
						<mix:BasicImageParameters>
							<mix:Format>
								<mix:MIMEType>image/jp2</mix:MIMEType>
								<mix:ByteOrder>little-endian</mix:ByteOrder>
								<mix:Compression>
									<mix:CompressionScheme>34712</mix:CompressionScheme>
								</mix:Compression>
								<mix:PhotometricInterpretation>
									<mix:ColorSpace>2</mix:ColorSpace>
								</mix:PhotometricInterpretation>
							</mix:Format>
							<mix:File>
								<mix:ImageIdentifier imageIdentifierLocation="//fileserver3/OUT6/PUL-DaliborMusicJournal/Dalibor/bmtnabd/issues/1894/10/20_01/alto">bmtnabd_1894-10-20_01_0007.jp2</mix:ImageIdentifier>
								<mix:FileSize>4514725</mix:FileSize>
								<mix:Orientation>1</mix:Orientation>
								<mix:DisplayOrientation>1</mix:DisplayOrientation>
							</mix:File>
						</mix:BasicImageParameters>
						<mix:ImageCreation>
							<mix:SourceType>METAe_Serial</mix:SourceType>
							<mix:SourceID/>
							<mix:ImageProducer/>
							<mix:Host>
								<mix:HostComputer>DWP4</mix:HostComputer>
								<mix:OperatingSystem>windows</mix:OperatingSystem>
								<mix:OSVersion>7 SP1</mix:OSVersion>
							</mix:Host>
							<mix:DeviceSource/>
							<mix:ScanningSystemCapture>
								<mix:ScanningSystemHardware>
									<mix:ScannerManufacturer/>
									<mix:ScannerModel>
										<mix:ScannerModelName/>
										<mix:ScannerModelNumber/>
										<mix:ScannerModelSerialNo/>
									</mix:ScannerModel>
								</mix:ScanningSystemHardware>
								<mix:ScanningSystemSoftware>
									<mix:ScanningSoftware>CCS docWorks</mix:ScanningSoftware>
									<mix:ScanningSoftwareVersionNo/>
								</mix:ScanningSystemSoftware>
								<mix:ScannerCaptureSettings>
									<mix:PixelSize>0.0423333</mix:PixelSize>
									<mix:PhysScanResolution>
										<mix:XphysScanResolution>600</mix:XphysScanResolution>
										<mix:YphysScanResolution>600</mix:YphysScanResolution>
									</mix:PhysScanResolution>
								</mix:ScannerCaptureSettings>
							</mix:ScanningSystemCapture>
						</mix:ImageCreation>
						<mix:ImagingPerformanceAssessment>
							<mix:SpatialMetrics>
								<mix:ImageWidth>5304</mix:ImageWidth>
								<mix:ImageLength>6808</mix:ImageLength>
							</mix:SpatialMetrics>
							<mix:Energetics>
								<mix:BitsPerSample>8,8,8</mix:BitsPerSample>
								<mix:SamplesPerPixel>3</mix:SamplesPerPixel>
							</mix:Energetics>
						</mix:ImagingPerformanceAssessment>
						<mix:ChangeHistory>
							<mix:ImageProcessing>
								<mix:SourceData>./PUL-DaliborMusicJournal/1894/10/20_01/00000335.tif</mix:SourceData>
							</mix:ImageProcessing>
						</mix:ChangeHistory>
					</mix:mix>
				</xmlData>
			</mdWrap>
		</techMD>
		<techMD ID="techmd8">
			<mdWrap MDTYPE="NISOIMG">
				<xmlData>
					<mix:mix>
						<mix:BasicImageParameters>
							<mix:Format>
								<mix:MIMEType>image/jp2</mix:MIMEType>
								<mix:ByteOrder>little-endian</mix:ByteOrder>
								<mix:Compression>
									<mix:CompressionScheme>34712</mix:CompressionScheme>
								</mix:Compression>
								<mix:PhotometricInterpretation>
									<mix:ColorSpace>2</mix:ColorSpace>
								</mix:PhotometricInterpretation>
							</mix:Format>
							<mix:File>
								<mix:ImageIdentifier imageIdentifierLocation="//fileserver3/OUT6/PUL-DaliborMusicJournal/Dalibor/bmtnabd/issues/1894/10/20_01/alto">bmtnabd_1894-10-20_01_0008.jp2</mix:ImageIdentifier>
								<mix:FileSize>4378204</mix:FileSize>
								<mix:Orientation>1</mix:Orientation>
								<mix:DisplayOrientation>1</mix:DisplayOrientation>
							</mix:File>
						</mix:BasicImageParameters>
						<mix:ImageCreation>
							<mix:SourceType>METAe_Serial</mix:SourceType>
							<mix:SourceID/>
							<mix:ImageProducer/>
							<mix:Host>
								<mix:HostComputer>DWP4</mix:HostComputer>
								<mix:OperatingSystem>windows</mix:OperatingSystem>
								<mix:OSVersion>7 SP1</mix:OSVersion>
							</mix:Host>
							<mix:DeviceSource/>
							<mix:ScanningSystemCapture>
								<mix:ScanningSystemHardware>
									<mix:ScannerManufacturer/>
									<mix:ScannerModel>
										<mix:ScannerModelName/>
										<mix:ScannerModelNumber/>
										<mix:ScannerModelSerialNo/>
									</mix:ScannerModel>
								</mix:ScanningSystemHardware>
								<mix:ScanningSystemSoftware>
									<mix:ScanningSoftware>CCS docWorks</mix:ScanningSoftware>
									<mix:ScanningSoftwareVersionNo/>
								</mix:ScanningSystemSoftware>
								<mix:ScannerCaptureSettings>
									<mix:PixelSize>0.0423333</mix:PixelSize>
									<mix:PhysScanResolution>
										<mix:XphysScanResolution>600</mix:XphysScanResolution>
										<mix:YphysScanResolution>600</mix:YphysScanResolution>
									</mix:PhysScanResolution>
								</mix:ScannerCaptureSettings>
							</mix:ScanningSystemCapture>
						</mix:ImageCreation>
						<mix:ImagingPerformanceAssessment>
							<mix:SpatialMetrics>
								<mix:ImageWidth>5161</mix:ImageWidth>
								<mix:ImageLength>6785</mix:ImageLength>
							</mix:SpatialMetrics>
							<mix:Energetics>
								<mix:BitsPerSample>8,8,8</mix:BitsPerSample>
								<mix:SamplesPerPixel>3</mix:SamplesPerPixel>
							</mix:Energetics>
						</mix:ImagingPerformanceAssessment>
						<mix:ChangeHistory>
							<mix:ImageProcessing>
								<mix:SourceData>./PUL-DaliborMusicJournal/1894/10/20_01/00000336.tif</mix:SourceData>
							</mix:ImageProcessing>
						</mix:ChangeHistory>
					</mix:mix>
				</xmlData>
			</mdWrap>
		</techMD>
		<techMD ID="techmd9">
			<mdWrap MDTYPE="NISOIMG">
				<xmlData>
					<mix:mix>
						<mix:BasicImageParameters>
							<mix:Format>
								<mix:MIMEType>image/jp2</mix:MIMEType>
								<mix:ByteOrder>little-endian</mix:ByteOrder>
								<mix:Compression>
									<mix:CompressionScheme>34712</mix:CompressionScheme>
								</mix:Compression>
								<mix:PhotometricInterpretation>
									<mix:ColorSpace>2</mix:ColorSpace>
								</mix:PhotometricInterpretation>
							</mix:Format>
							<mix:File>
								<mix:ImageIdentifier imageIdentifierLocation="//fileserver3/OUT6/PUL-DaliborMusicJournal/Dalibor/bmtnabd/issues/1894/10/20_01/alto">bmtnabd_1894-10-20_01_0009.jp2</mix:ImageIdentifier>
								<mix:FileSize>4372163</mix:FileSize>
								<mix:Orientation>1</mix:Orientation>
								<mix:DisplayOrientation>1</mix:DisplayOrientation>
							</mix:File>
						</mix:BasicImageParameters>
						<mix:ImageCreation>
							<mix:SourceType>METAe_Serial</mix:SourceType>
							<mix:SourceID/>
							<mix:ImageProducer/>
							<mix:Host>
								<mix:HostComputer>DWP4</mix:HostComputer>
								<mix:OperatingSystem>windows</mix:OperatingSystem>
								<mix:OSVersion>7 SP1</mix:OSVersion>
							</mix:Host>
							<mix:DeviceSource/>
							<mix:ScanningSystemCapture>
								<mix:ScanningSystemHardware>
									<mix:ScannerManufacturer/>
									<mix:ScannerModel>
										<mix:ScannerModelName/>
										<mix:ScannerModelNumber/>
										<mix:ScannerModelSerialNo/>
									</mix:ScannerModel>
								</mix:ScanningSystemHardware>
								<mix:ScanningSystemSoftware>
									<mix:ScanningSoftware>CCS docWorks</mix:ScanningSoftware>
									<mix:ScanningSoftwareVersionNo/>
								</mix:ScanningSystemSoftware>
								<mix:ScannerCaptureSettings>
									<mix:PixelSize>0.0423333</mix:PixelSize>
									<mix:PhysScanResolution>
										<mix:XphysScanResolution>600</mix:XphysScanResolution>
										<mix:YphysScanResolution>600</mix:YphysScanResolution>
									</mix:PhysScanResolution>
								</mix:ScannerCaptureSettings>
							</mix:ScanningSystemCapture>
						</mix:ImageCreation>
						<mix:ImagingPerformanceAssessment>
							<mix:SpatialMetrics>
								<mix:ImageWidth>5161</mix:ImageWidth>
								<mix:ImageLength>6778</mix:ImageLength>
							</mix:SpatialMetrics>
							<mix:Energetics>
								<mix:BitsPerSample>8,8,8</mix:BitsPerSample>
								<mix:SamplesPerPixel>3</mix:SamplesPerPixel>
							</mix:Energetics>
						</mix:ImagingPerformanceAssessment>
						<mix:ChangeHistory>
							<mix:ImageProcessing>
								<mix:SourceData>./PUL-DaliborMusicJournal/1894/10/20_01/00000337.tif</mix:SourceData>
							</mix:ImageProcessing>
						</mix:ChangeHistory>
					</mix:mix>
				</xmlData>
			</mdWrap>
		</techMD>
		<techMD ID="techmd10">
			<mdWrap MDTYPE="NISOIMG">
				<xmlData>
					<mix:mix>
						<mix:BasicImageParameters>
							<mix:Format>
								<mix:MIMEType>image/jp2</mix:MIMEType>
								<mix:ByteOrder>little-endian</mix:ByteOrder>
								<mix:Compression>
									<mix:CompressionScheme>34712</mix:CompressionScheme>
								</mix:Compression>
								<mix:PhotometricInterpretation>
									<mix:ColorSpace>2</mix:ColorSpace>
								</mix:PhotometricInterpretation>
							</mix:Format>
							<mix:File>
								<mix:ImageIdentifier imageIdentifierLocation="//fileserver3/OUT6/PUL-DaliborMusicJournal/Dalibor/bmtnabd/issues/1894/10/20_01/alto">bmtnabd_1894-10-20_01_0010.jp2</mix:ImageIdentifier>
								<mix:FileSize>4457188</mix:FileSize>
								<mix:Orientation>1</mix:Orientation>
								<mix:DisplayOrientation>1</mix:DisplayOrientation>
							</mix:File>
						</mix:BasicImageParameters>
						<mix:ImageCreation>
							<mix:SourceType>METAe_Serial</mix:SourceType>
							<mix:SourceID/>
							<mix:ImageProducer/>
							<mix:Host>
								<mix:HostComputer>DWP4</mix:HostComputer>
								<mix:OperatingSystem>windows</mix:OperatingSystem>
								<mix:OSVersion>7 SP1</mix:OSVersion>
							</mix:Host>
							<mix:DeviceSource/>
							<mix:ScanningSystemCapture>
								<mix:ScanningSystemHardware>
									<mix:ScannerManufacturer/>
									<mix:ScannerModel>
										<mix:ScannerModelName/>
										<mix:ScannerModelNumber/>
										<mix:ScannerModelSerialNo/>
									</mix:ScannerModel>
								</mix:ScanningSystemHardware>
								<mix:ScanningSystemSoftware>
									<mix:ScanningSoftware>CCS docWorks</mix:ScanningSoftware>
									<mix:ScanningSoftwareVersionNo/>
								</mix:ScanningSystemSoftware>
								<mix:ScannerCaptureSettings>
									<mix:PixelSize>0.0423333</mix:PixelSize>
									<mix:PhysScanResolution>
										<mix:XphysScanResolution>600</mix:XphysScanResolution>
										<mix:YphysScanResolution>600</mix:YphysScanResolution>
									</mix:PhysScanResolution>
								</mix:ScannerCaptureSettings>
							</mix:ScanningSystemCapture>
						</mix:ImageCreation>
						<mix:ImagingPerformanceAssessment>
							<mix:SpatialMetrics>
								<mix:ImageWidth>5231</mix:ImageWidth>
								<mix:ImageLength>6815</mix:ImageLength>
							</mix:SpatialMetrics>
							<mix:Energetics>
								<mix:BitsPerSample>8,8,8</mix:BitsPerSample>
								<mix:SamplesPerPixel>3</mix:SamplesPerPixel>
							</mix:Energetics>
						</mix:ImagingPerformanceAssessment>
						<mix:ChangeHistory>
							<mix:ImageProcessing>
								<mix:SourceData>./PUL-DaliborMusicJournal/1894/10/20_01/00000338.tif</mix:SourceData>
							</mix:ImageProcessing>
						</mix:ChangeHistory>
					</mix:mix>
				</xmlData>
			</mdWrap>
		</techMD>
		<techMD ID="techmd11">
			<mdWrap MDTYPE="NISOIMG">
				<xmlData>
					<mix:mix>
						<mix:BasicImageParameters>
							<mix:Format>
								<mix:MIMEType>image/jp2</mix:MIMEType>
								<mix:ByteOrder>little-endian</mix:ByteOrder>
								<mix:Compression>
									<mix:CompressionScheme>34712</mix:CompressionScheme>
								</mix:Compression>
								<mix:PhotometricInterpretation>
									<mix:ColorSpace>2</mix:ColorSpace>
								</mix:PhotometricInterpretation>
							</mix:Format>
							<mix:File>
								<mix:ImageIdentifier imageIdentifierLocation="//fileserver3/OUT6/PUL-DaliborMusicJournal/Dalibor/bmtnabd/issues/1894/10/20_01/alto">bmtnabd_1894-10-20_01_0011.jp2</mix:ImageIdentifier>
								<mix:FileSize>4457395</mix:FileSize>
								<mix:Orientation>1</mix:Orientation>
								<mix:DisplayOrientation>1</mix:DisplayOrientation>
							</mix:File>
						</mix:BasicImageParameters>
						<mix:ImageCreation>
							<mix:SourceType>METAe_Serial</mix:SourceType>
							<mix:SourceID/>
							<mix:ImageProducer/>
							<mix:Host>
								<mix:HostComputer>DWP4</mix:HostComputer>
								<mix:OperatingSystem>windows</mix:OperatingSystem>
								<mix:OSVersion>7 SP1</mix:OSVersion>
							</mix:Host>
							<mix:DeviceSource/>
							<mix:ScanningSystemCapture>
								<mix:ScanningSystemHardware>
									<mix:ScannerManufacturer/>
									<mix:ScannerModel>
										<mix:ScannerModelName/>
										<mix:ScannerModelNumber/>
										<mix:ScannerModelSerialNo/>
									</mix:ScannerModel>
								</mix:ScanningSystemHardware>
								<mix:ScanningSystemSoftware>
									<mix:ScanningSoftware>CCS docWorks</mix:ScanningSoftware>
									<mix:ScanningSoftwareVersionNo/>
								</mix:ScanningSystemSoftware>
								<mix:ScannerCaptureSettings>
									<mix:PixelSize>0.0423333</mix:PixelSize>
									<mix:PhysScanResolution>
										<mix:XphysScanResolution>600</mix:XphysScanResolution>
										<mix:YphysScanResolution>600</mix:YphysScanResolution>
									</mix:PhysScanResolution>
								</mix:ScannerCaptureSettings>
							</mix:ScanningSystemCapture>
						</mix:ImageCreation>
						<mix:ImagingPerformanceAssessment>
							<mix:SpatialMetrics>
								<mix:ImageWidth>5232</mix:ImageWidth>
								<mix:ImageLength>6815</mix:ImageLength>
							</mix:SpatialMetrics>
							<mix:Energetics>
								<mix:BitsPerSample>8,8,8</mix:BitsPerSample>
								<mix:SamplesPerPixel>3</mix:SamplesPerPixel>
							</mix:Energetics>
						</mix:ImagingPerformanceAssessment>
						<mix:ChangeHistory>
							<mix:ImageProcessing>
								<mix:SourceData>./PUL-DaliborMusicJournal/1894/10/20_01/00000339.tif</mix:SourceData>
							</mix:ImageProcessing>
						</mix:ChangeHistory>
					</mix:mix>
				</xmlData>
			</mdWrap>
		</techMD>
		<techMD ID="techmd12">
			<mdWrap MDTYPE="NISOIMG">
				<xmlData>
					<mix:mix>
						<mix:BasicImageParameters>
							<mix:Format>
								<mix:MIMEType>image/jp2</mix:MIMEType>
								<mix:ByteOrder>little-endian</mix:ByteOrder>
								<mix:Compression>
									<mix:CompressionScheme>34712</mix:CompressionScheme>
								</mix:Compression>
								<mix:PhotometricInterpretation>
									<mix:ColorSpace>2</mix:ColorSpace>
								</mix:PhotometricInterpretation>
							</mix:Format>
							<mix:File>
								<mix:ImageIdentifier imageIdentifierLocation="//fileserver3/OUT6/PUL-DaliborMusicJournal/Dalibor/bmtnabd/issues/1894/10/20_01/alto">bmtnabd_1894-10-20_01_0012.jp2</mix:ImageIdentifier>
								<mix:FileSize>4483249</mix:FileSize>
								<mix:Orientation>1</mix:Orientation>
								<mix:DisplayOrientation>1</mix:DisplayOrientation>
							</mix:File>
						</mix:BasicImageParameters>
						<mix:ImageCreation>
							<mix:SourceType>METAe_Serial</mix:SourceType>
							<mix:SourceID/>
							<mix:ImageProducer/>
							<mix:Host>
								<mix:HostComputer>DWP4</mix:HostComputer>
								<mix:OperatingSystem>windows</mix:OperatingSystem>
								<mix:OSVersion>7 SP1</mix:OSVersion>
							</mix:Host>
							<mix:DeviceSource/>
							<mix:ScanningSystemCapture>
								<mix:ScanningSystemHardware>
									<mix:ScannerManufacturer/>
									<mix:ScannerModel>
										<mix:ScannerModelName/>
										<mix:ScannerModelNumber/>
										<mix:ScannerModelSerialNo/>
									</mix:ScannerModel>
								</mix:ScanningSystemHardware>
								<mix:ScanningSystemSoftware>
									<mix:ScanningSoftware>CCS docWorks</mix:ScanningSoftware>
									<mix:ScanningSoftwareVersionNo/>
								</mix:ScanningSystemSoftware>
								<mix:ScannerCaptureSettings>
									<mix:PixelSize>0.0423333</mix:PixelSize>
									<mix:PhysScanResolution>
										<mix:XphysScanResolution>600</mix:XphysScanResolution>
										<mix:YphysScanResolution>600</mix:YphysScanResolution>
									</mix:PhysScanResolution>
								</mix:ScannerCaptureSettings>
							</mix:ScanningSystemCapture>
						</mix:ImageCreation>
						<mix:ImagingPerformanceAssessment>
							<mix:SpatialMetrics>
								<mix:ImageWidth>5267</mix:ImageWidth>
								<mix:ImageLength>6808</mix:ImageLength>
							</mix:SpatialMetrics>
							<mix:Energetics>
								<mix:BitsPerSample>8,8,8</mix:BitsPerSample>
								<mix:SamplesPerPixel>3</mix:SamplesPerPixel>
							</mix:Energetics>
						</mix:ImagingPerformanceAssessment>
						<mix:ChangeHistory>
							<mix:ImageProcessing>
								<mix:SourceData>./PUL-DaliborMusicJournal/1894/10/20_01/00000340.tif</mix:SourceData>
							</mix:ImageProcessing>
						</mix:ChangeHistory>
					</mix:mix>
				</xmlData>
			</mdWrap>
		</techMD>
	</amdSec>
	<fileSec>
		<fileGrp ID="IMGGRP" USE="Images">
			<file ID="IMG00001" ADMID="techmd1" GROUPID="page1" CREATED="2018-09-24T23:24:34" MIMETYPE="image/jp2" SEQ="1" CHECKSUM="5a2b52ab35694dba2f204980867caf11c496cf95" CHECKSUMTYPE="SHA-1" SIZE="4514070">
				<FLocat LOCTYPE="URL" xlink:href="file:///usr/share/BlueMountain/astore/periodicals/bmtnabd/issues/1894/10/20_01/delivery/bmtnabd_1894-10-20_01_0001.jp2"/>
			</file>
			<file ID="IMG00002" ADMID="techmd2" GROUPID="page2" CREATED="2018-09-24T23:25:05" MIMETYPE="image/jp2" SEQ="2" CHECKSUM="5e0808d6ca909e931a351dd87b13a290b57d9a95" CHECKSUMTYPE="SHA-1" SIZE="4512558">
				<FLocat LOCTYPE="URL" xlink:href="file:///usr/share/BlueMountain/astore/periodicals/bmtnabd/issues/1894/10/20_01/delivery/bmtnabd_1894-10-20_01_0002.jp2"/>
			</file>
			<file ID="IMG00003" ADMID="techmd3" GROUPID="page3" CREATED="2018-09-24T23:25:46" MIMETYPE="image/jp2" SEQ="3" CHECKSUM="3f2323da37d5ed7fcd790b31c5d1e3248a7e2dc2" CHECKSUMTYPE="SHA-1" SIZE="4508799">
				<FLocat LOCTYPE="URL" xlink:href="file:///usr/share/BlueMountain/astore/periodicals/bmtnabd/issues/1894/10/20_01/delivery/bmtnabd_1894-10-20_01_0003.jp2"/>
			</file>
			<file ID="IMG00004" ADMID="techmd4" GROUPID="page4" CREATED="2018-09-24T23:26:09" MIMETYPE="image/jp2" SEQ="4" CHECKSUM="c64aa7e1c75ca9178dac507d2f93c69de632f296" CHECKSUMTYPE="SHA-1" SIZE="4521717">
				<FLocat LOCTYPE="URL" xlink:href="file:///usr/share/BlueMountain/astore/periodicals/bmtnabd/issues/1894/10/20_01/delivery/bmtnabd_1894-10-20_01_0004.jp2"/>
			</file>
			<file ID="IMG00005" ADMID="techmd5" GROUPID="page5" CREATED="2018-09-24T23:26:39" MIMETYPE="image/jp2" SEQ="5" CHECKSUM="a1a74329e1cb68c1166b57f801920581c8e83e5a" CHECKSUMTYPE="SHA-1" SIZE="4522608">
				<FLocat LOCTYPE="URL" xlink:href="file:///usr/share/BlueMountain/astore/periodicals/bmtnabd/issues/1894/10/20_01/delivery/bmtnabd_1894-10-20_01_0005.jp2"/>
			</file>
			<file ID="IMG00006" ADMID="techmd6" GROUPID="page6" CREATED="2018-09-24T23:27:05" MIMETYPE="image/jp2" SEQ="6" CHECKSUM="ee556d8f459b362e860aba1b4e17f379def5984f" CHECKSUMTYPE="SHA-1" SIZE="4513870">
				<FLocat LOCTYPE="URL" xlink:href="file:///usr/share/BlueMountain/astore/periodicals/bmtnabd/issues/1894/10/20_01/delivery/bmtnabd_1894-10-20_01_0006.jp2"/>
			</file>
			<file ID="IMG00007" ADMID="techmd7" GROUPID="page7" CREATED="2018-09-24T23:27:40" MIMETYPE="image/jp2" SEQ="7" CHECKSUM="c063142ee64318f37697cfbd79db61a10bd6b37e" CHECKSUMTYPE="SHA-1" SIZE="4514725">
				<FLocat LOCTYPE="URL" xlink:href="file:///usr/share/BlueMountain/astore/periodicals/bmtnabd/issues/1894/10/20_01/delivery/bmtnabd_1894-10-20_01_0007.jp2"/>
			</file>
			<file ID="IMG00008" ADMID="techmd8" GROUPID="page8" CREATED="2018-09-24T23:28:09" MIMETYPE="image/jp2" SEQ="8" CHECKSUM="2d8f474a19cba1e53f2177e25e418d18d3739565" CHECKSUMTYPE="SHA-1" SIZE="4378204">
				<FLocat LOCTYPE="URL" xlink:href="file:///usr/share/BlueMountain/astore/periodicals/bmtnabd/issues/1894/10/20_01/delivery/bmtnabd_1894-10-20_01_0008.jp2"/>
			</file>
			<file ID="IMG00009" ADMID="techmd9" GROUPID="page9" CREATED="2018-09-24T23:28:34" MIMETYPE="image/jp2" SEQ="9" CHECKSUM="2afe990ca77f84692b8603b9b4558c2ba2a4618d" CHECKSUMTYPE="SHA-1" SIZE="4372163">
				<FLocat LOCTYPE="URL" xlink:href="file:///usr/share/BlueMountain/astore/periodicals/bmtnabd/issues/1894/10/20_01/delivery/bmtnabd_1894-10-20_01_0009.jp2"/>
			</file>
			<file ID="IMG00010" ADMID="techmd10" GROUPID="page10" CREATED="2018-09-24T23:28:56" MIMETYPE="image/jp2" SEQ="10" CHECKSUM="865d416fb695b6432450a3f27d0cf16b2c1cc610" CHECKSUMTYPE="SHA-1" SIZE="4457188">
				<FLocat LOCTYPE="URL" xlink:href="file:///usr/share/BlueMountain/astore/periodicals/bmtnabd/issues/1894/10/20_01/delivery/bmtnabd_1894-10-20_01_0010.jp2"/>
			</file>
			<file ID="IMG00011" ADMID="techmd11" GROUPID="page11" CREATED="2018-09-24T23:29:22" MIMETYPE="image/jp2" SEQ="11" CHECKSUM="6413fcb6b82eab438ab871fd9c7527d03650c86f" CHECKSUMTYPE="SHA-1" SIZE="4457395">
				<FLocat LOCTYPE="URL" xlink:href="file:///usr/share/BlueMountain/astore/periodicals/bmtnabd/issues/1894/10/20_01/delivery/bmtnabd_1894-10-20_01_0011.jp2"/>
			</file>
			<file ID="IMG00012" ADMID="techmd12" GROUPID="page12" CREATED="2018-09-24T23:30:13" MIMETYPE="image/jp2" SEQ="12" CHECKSUM="4838923bb71c07d2b063b5d4d99934ce0821a7e0" CHECKSUMTYPE="SHA-1" SIZE="4483249">
				<FLocat LOCTYPE="URL" xlink:href="file:///usr/share/BlueMountain/astore/periodicals/bmtnabd/issues/1894/10/20_01/delivery/bmtnabd_1894-10-20_01_0012.jp2"/>
			</file>
		</fileGrp>
		<fileGrp ID="ALTOGRP" USE="OCR">
			<file ID="ALTO00001" GROUPID="page1" CREATED="2018-09-24T23:30:40" MIMETYPE="text/xml" CHECKSUM="02a21a456ba1ef062334df866aec1a4378db73a3" CHECKSUMTYPE="SHA-1" SIZE="147423">
				<FLocat LOCTYPE="URL" xlink:href="file://./alto/bmtnabd_1894-10-20_01_0001.alto.xml"/>
			</file>
			<file ID="ALTO00002" GROUPID="page2" CREATED="2018-09-24T23:30:41" MIMETYPE="text/xml" CHECKSUM="53061e79946eb270e554ea7a5fe20c51144bfb09" CHECKSUMTYPE="SHA-1" SIZE="189665">
				<FLocat LOCTYPE="URL" xlink:href="file://./alto/bmtnabd_1894-10-20_01_0002.alto.xml"/>
			</file>
			<file ID="ALTO00003" GROUPID="page3" CREATED="2018-09-24T23:30:41" MIMETYPE="text/xml" CHECKSUM="a4c71ccb3dbfbdfc52b99de8d701020e8a4a7087" CHECKSUMTYPE="SHA-1" SIZE="170644">
				<FLocat LOCTYPE="URL" xlink:href="file://./alto/bmtnabd_1894-10-20_01_0003.alto.xml"/>
			</file>
			<file ID="ALTO00004" GROUPID="page4" CREATED="2018-09-24T23:30:42" MIMETYPE="text/xml" CHECKSUM="a92d4ae85d856c876c1a35520800fee5ed9d0aaa" CHECKSUMTYPE="SHA-1" SIZE="179933">
				<FLocat LOCTYPE="URL" xlink:href="file://./alto/bmtnabd_1894-10-20_01_0004.alto.xml"/>
			</file>
			<file ID="ALTO00005" GROUPID="page5" CREATED="2018-09-24T23:30:42" MIMETYPE="text/xml" CHECKSUM="c27c766f0ba7a450f30662b7234ab40d73b4b267" CHECKSUMTYPE="SHA-1" SIZE="175813">
				<FLocat LOCTYPE="URL" xlink:href="file://./alto/bmtnabd_1894-10-20_01_0005.alto.xml"/>
			</file>
			<file ID="ALTO00006" GROUPID="page6" CREATED="2018-09-24T23:30:42" MIMETYPE="text/xml" CHECKSUM="a75264a0259ad01f9d564565ab7bf3f5086ad0ee" CHECKSUMTYPE="SHA-1" SIZE="250033">
				<FLocat LOCTYPE="URL" xlink:href="file://./alto/bmtnabd_1894-10-20_01_0006.alto.xml"/>
			</file>
			<file ID="ALTO00007" GROUPID="page7" CREATED="2018-09-24T23:30:43" MIMETYPE="text/xml" CHECKSUM="f353682b8c3193d4fdc4f145bd50cad76e59c648" CHECKSUMTYPE="SHA-1" SIZE="263502">
				<FLocat LOCTYPE="URL" xlink:href="file://./alto/bmtnabd_1894-10-20_01_0007.alto.xml"/>
			</file>
			<file ID="ALTO00008" GROUPID="page8" CREATED="2018-09-24T23:30:44" MIMETYPE="text/xml" CHECKSUM="d3ff2c34efacd49cc2d1f8df42546a45ae3a96f9" CHECKSUMTYPE="SHA-1" SIZE="246348">
				<FLocat LOCTYPE="URL" xlink:href="file://./alto/bmtnabd_1894-10-20_01_0008.alto.xml"/>
			</file>
			<file ID="ALTO00009" GROUPID="page9" CREATED="2018-09-24T23:30:44" MIMETYPE="text/xml" CHECKSUM="7df6c327e294ba6f3095f48bad71e6cd9c03fe4e" CHECKSUMTYPE="SHA-1" SIZE="253528">
				<FLocat LOCTYPE="URL" xlink:href="file://./alto/bmtnabd_1894-10-20_01_0009.alto.xml"/>
			</file>
			<file ID="ALTO00010" GROUPID="page10" CREATED="2018-09-24T23:30:45" MIMETYPE="text/xml" CHECKSUM="74e5145f9ffc0e1fbf17f820747d14705379674b" CHECKSUMTYPE="SHA-1" SIZE="256802">
				<FLocat LOCTYPE="URL" xlink:href="file://./alto/bmtnabd_1894-10-20_01_0010.alto.xml"/>
			</file>
			<file ID="ALTO00011" GROUPID="page11" CREATED="2018-09-24T23:30:46" MIMETYPE="text/xml" CHECKSUM="2dc5cd16fc635b483b54be62b56cfba862cc0c0f" CHECKSUMTYPE="SHA-1" SIZE="179794">
				<FLocat LOCTYPE="URL" xlink:href="file://./alto/bmtnabd_1894-10-20_01_0011.alto.xml"/>
			</file>
			<file ID="ALTO00012" GROUPID="page12" CREATED="2018-09-24T23:30:46" MIMETYPE="text/xml" CHECKSUM="28b90fe7437901fe8f6f83c43f9d235af733b772" CHECKSUMTYPE="SHA-1" SIZE="111801">
				<FLocat LOCTYPE="URL" xlink:href="file://./alto/bmtnabd_1894-10-20_01_0012.alto.xml"/>
			</file>
		</fileGrp>
		<fileGrp ID="PDFGRP" USE="PDF">
			<file ID="PDF_ISSUELEVEL" CREATED="2018-09-24T23:31:37" MIMETYPE="application/pdf" CHECKSUM="10a71c42808471bcf7b7f106be68a89259b05af9" CHECKSUMTYPE="SHA-1" SIZE="4069579">
				<FLocat LOCTYPE="URL" xlink:href="file:///usr/share/BlueMountain/astore/periodicals/bmtnabd/issues/1894/10/20_01/bmtnabd_1894-10-20_01.pdf"/>
			</file>
		</fileGrp>
	</fileSec>
	<structMap LABEL="Physical Structure" TYPE="PHYSICAL">
		<div ID="DIVP1" LABEL="" TYPE="Magazine" DMDID="dmd1">
			<div ID="DIVP2" ORDER="1" ORDERLABEL="1" TYPE="INSIDE">
				<fptr>
					<par>
						<area FILEID="IMG00001"/>
						<area FILEID="ALTO00001" BETYPE="IDREF" BEGIN="P1"/>
					</par>
				</fptr>
			</div>
			<div ID="DIVP3" ORDER="2" ORDERLABEL="2" LABEL="322" TYPE="INSIDE">
				<fptr>
					<par>
						<area FILEID="IMG00002"/>
						<area FILEID="ALTO00002" BETYPE="IDREF" BEGIN="P2"/>
					</par>
				</fptr>
			</div>
			<div ID="DIVP4" ORDER="3" ORDERLABEL="3" LABEL="323" TYPE="INSIDE">
				<fptr>
					<par>
						<area FILEID="IMG00003"/>
						<area FILEID="ALTO00003" BETYPE="IDREF" BEGIN="P3"/>
					</par>
				</fptr>
			</div>
			<div ID="DIVP5" ORDER="4" ORDERLABEL="4" LABEL="324" TYPE="INSIDE">
				<fptr>
					<par>
						<area FILEID="IMG00004"/>
						<area FILEID="ALTO00004" BETYPE="IDREF" BEGIN="P4"/>
					</par>
				</fptr>
			</div>
			<div ID="DIVP6" ORDER="5" ORDERLABEL="5" LABEL="325" TYPE="INSIDE">
				<fptr>
					<par>
						<area FILEID="IMG00005"/>
						<area FILEID="ALTO00005" BETYPE="IDREF" BEGIN="P5"/>
					</par>
				</fptr>
			</div>
			<div ID="DIVP7" ORDER="6" ORDERLABEL="6" LABEL="326" TYPE="INSIDE">
				<fptr>
					<par>
						<area FILEID="IMG00006"/>
						<area FILEID="ALTO00006" BETYPE="IDREF" BEGIN="P6"/>
					</par>
				</fptr>
			</div>
			<div ID="DIVP8" ORDER="7" ORDERLABEL="7" LABEL="327" TYPE="INSIDE">
				<fptr>
					<par>
						<area FILEID="IMG00007"/>
						<area FILEID="ALTO00007" BETYPE="IDREF" BEGIN="P7"/>
					</par>
				</fptr>
			</div>
			<div ID="DIVP9" ORDER="8" ORDERLABEL="8" LABEL="328" TYPE="INSIDE">
				<fptr>
					<par>
						<area FILEID="IMG00008"/>
						<area FILEID="ALTO00008" BETYPE="IDREF" BEGIN="P8"/>
					</par>
				</fptr>
			</div>
			<div ID="DIVP10" ORDER="9" ORDERLABEL="9" LABEL="329" TYPE="INSIDE">
				<fptr>
					<par>
						<area FILEID="IMG00009"/>
						<area FILEID="ALTO00009" BETYPE="IDREF" BEGIN="P9"/>
					</par>
				</fptr>
			</div>
			<div ID="DIVP11" ORDER="10" ORDERLABEL="10" LABEL="330" TYPE="INSIDE">
				<fptr>
					<par>
						<area FILEID="IMG00010"/>
						<area FILEID="ALTO00010" BETYPE="IDREF" BEGIN="P10"/>
					</par>
				</fptr>
			</div>
			<div ID="DIVP12" ORDER="11" ORDERLABEL="11" LABEL="331" TYPE="INSIDE">
				<fptr>
					<par>
						<area FILEID="IMG00011"/>
						<area FILEID="ALTO00011" BETYPE="IDREF" BEGIN="P11"/>
					</par>
				</fptr>
			</div>
			<div ID="DIVP13" ORDER="12" ORDERLABEL="12" LABEL="332" TYPE="INSIDE">
				<fptr>
					<par>
						<area FILEID="IMG00012"/>
						<area FILEID="ALTO00012" BETYPE="IDREF" BEGIN="P12"/>
					</par>
				</fptr>
			</div>
		</div>
	</structMap>
	<structMap LABEL="Logical Structure" TYPE="LOGICAL">
		<div ID="L.1" TYPE="Magazine" LABEL="Dalibor">
			<div ID="L.1.1" TYPE="Issue" LABEL="Dalibor no. 42 20.10.1894">
				<div ID="L.1.1.1" TYPE="PublicationInfo" LABEL="Publication Information">
					<div ID="L.1.1.1.1" TYPE="GenericPubInfo" ORDER="1">
						<fptr>
							<area BETYPE="IDREF" FILEID="ALTO00001" BEGIN="P1_TB00011"/>
						</fptr>
					</div>
					<div ID="L.1.1.1.2" TYPE="GenericPubInfo" ORDER="2">
						<fptr>
							<area BETYPE="IDREF" FILEID="ALTO00001" BEGIN="P1_TB00010"/>
						</fptr>
					</div>
					<div ID="L.1.1.1.3" TYPE="GenericPubInfo" ORDER="3">
						<fptr>
							<area BETYPE="IDREF" FILEID="ALTO00001" BEGIN="P1_TB00009"/>
						</fptr>
					</div>
					<div ID="L.1.1.1.4" TYPE="GenericPubInfo" ORDER="4">
						<fptr>
							<area BETYPE="IDREF" FILEID="ALTO00001" BEGIN="P1_TB00008"/>
						</fptr>
					</div>
					<div ID="L.1.1.1.5" TYPE="GenericPubInfo" ORDER="5">
						<fptr>
							<area BETYPE="IDREF" FILEID="ALTO00012" BEGIN="P12_TB00002"/>
						</fptr>
					</div>
				</div>
				<div ID="L.1.1.2" TYPE="TextContent" ORDER="2" DMDID="c001" LABEL="HUDEBNÍ LISTY.">
					<div ID="L.1.1.2.1" TYPE="Head">
						<fptr>
							<area BETYPE="IDREF" FILEID="ALTO00001" BEGIN="P1_TB00001"/>
						</fptr>
					</div>
					<div ID="L.1.1.2.2" TYPE="Copy">
						<div ID="L.1.1.2.2.1" TYPE="BodyContent">
							<div ID="L.1.1.2.2.1.1" TYPE="Paragraph" ORDER="1">
								<div ID="L.1.1.2.2.1.1.1" TYPE="Text">
									<fptr>
										<area BETYPE="IDREF" FILEID="ALTO00001" BEGIN="P1_TB00002"/>
									</fptr>
								</div>
							</div>
						</div>
					</div>
				</div>
				<div ID="L.1.1.3" TYPE="TextContent" ORDER="3" DMDID="c002" LABEL="OBSAH:">
					<div ID="L.1.1.3.1" TYPE="Head">
						<fptr>
							<area BETYPE="IDREF" FILEID="ALTO00001" BEGIN="P1_TB00003"/>
						</fptr>
					</div>
					<div ID="L.1.1.3.2" TYPE="Copy">
						<div ID="L.1.1.3.2.1" TYPE="BodyContent">
							<div ID="L.1.1.3.2.1.1" TYPE="Paragraph" ORDER="1">
								<div ID="L.1.1.3.2.1.1.1" TYPE="Text">
									<fptr>
										<area BETYPE="IDREF" FILEID="ALTO00001" BEGIN="P1_TB00004"/>
									</fptr>
								</div>
							</div>
						</div>
					</div>
				</div>
				<div ID="L.1.1.4" TYPE="TextContent" ORDER="4" DMDID="c003" LABEL="NÁRODNÍ DIVADLO V PRAZE.">
					<div ID="L.1.1.4.1" TYPE="Head">
						<fptr>
							<area BETYPE="IDREF" FILEID="ALTO00001" BEGIN="P1_TB00005"/>
						</fptr>
					</div>
					<div ID="L.1.1.4.2" TYPE="Copy">
						<div ID="L.1.1.4.2.1" TYPE="BodyContent">
							<div ID="L.1.1.4.2.1.1" TYPE="Paragraph" ORDER="1">
								<div ID="L.1.1.4.2.1.1.1" TYPE="Text">
									<fptr>
										<seq>
											<area BETYPE="IDREF" FILEID="ALTO00001" BEGIN="P1_TB00006"/>
											<area BETYPE="IDREF" FILEID="ALTO00001" BEGIN="P1_TB00007"/>
										</seq>
									</fptr>
								</div>
							</div>
							<div ID="L.1.1.4.2.1.2" TYPE="Paragraph" ORDER="2">
								<div ID="L.1.1.4.2.1.2.1" TYPE="Text">
									<fptr>
										<seq>
											<area BETYPE="IDREF" FILEID="ALTO00002" BEGIN="P2_TB00001"/>
											<area BETYPE="IDREF" FILEID="ALTO00002" BEGIN="P2_TB00002"/>
										</seq>
									</fptr>
								</div>
							</div>
							<div ID="L.1.1.4.2.1.3" TYPE="Paragraph" ORDER="3">
								<div ID="L.1.1.4.2.1.3.1" TYPE="Text">
									<fptr>
										<area BETYPE="IDREF" FILEID="ALTO00003" BEGIN="P3_TB00001"/>
									</fptr>
								</div>
							</div>
							<div ID="L.1.1.4.2.1.4" TYPE="Paragraph" ORDER="4">
								<div ID="L.1.1.4.2.1.4.1" TYPE="Text">
									<fptr>
										<seq>
											<area BETYPE="IDREF" FILEID="ALTO00003" BEGIN="P3_TB00002"/>
											<area BETYPE="IDREF" FILEID="ALTO00003" BEGIN="P3_TB00003"/>
										</seq>
									</fptr>
								</div>
							</div>
						</div>
					</div>
				</div>
				<div ID="L.1.1.5" TYPE="TextContent" ORDER="5" DMDID="c004" LABEL="Z KONCERTNÍ SÍNĚ.">
					<div ID="L.1.1.5.1" TYPE="Head">
						<fptr>
							<area BETYPE="IDREF" FILEID="ALTO00003" BEGIN="P3_TB00004"/>
						</fptr>
					</div>
					<div ID="L.1.1.5.2" TYPE="Copy">
						<div ID="L.1.1.5.2.1" TYPE="BodyContent">
							<div ID="L.1.1.5.2.1.1" TYPE="Paragraph" ORDER="1">
								<div ID="L.1.1.5.2.1.1.1" TYPE="Text">
									<fptr>
										<seq>
											<area BETYPE="IDREF" FILEID="ALTO00003" BEGIN="P3_TB00005"/>
											<area BETYPE="IDREF" FILEID="ALTO00004" BEGIN="P4_TB00001"/>
										</seq>
									</fptr>
								</div>
							</div>
							<div ID="L.1.1.5.2.1.2" TYPE="Paragraph" ORDER="2">
								<div ID="L.1.1.5.2.1.2.1" TYPE="Text">
									<fptr>
										<seq>
											<area BETYPE="IDREF" FILEID="ALTO00004" BEGIN="P4_TB00002"/>
											<area BETYPE="IDREF" FILEID="ALTO00004" BEGIN="P4_TB00003"/>
										</seq>
									</fptr>
								</div>
							</div>
							<div ID="L.1.1.5.2.1.3" TYPE="Paragraph" ORDER="3">
								<div ID="L.1.1.5.2.1.3.1" TYPE="Text">
									<fptr>
										<area BETYPE="IDREF" FILEID="ALTO00005" BEGIN="P5_TB00001"/>
									</fptr>
								</div>
							</div>
						</div>
					</div>
				</div>
				<div ID="L.1.1.6" TYPE="TextContent" ORDER="6" DMDID="c005" LABEL="LITERATURA,">
					<div ID="L.1.1.6.1" TYPE="Head">
						<fptr>
							<area BETYPE="IDREF" FILEID="ALTO00005" BEGIN="P5_TB00002"/>
						</fptr>
					</div>
					<div ID="L.1.1.6.2" TYPE="Copy">
						<div ID="L.1.1.6.2.1" TYPE="BodyContent">
							<div ID="L.1.1.6.2.1.1" TYPE="Paragraph" ORDER="1">
								<div ID="L.1.1.6.2.1.1.1" TYPE="Text">
									<fptr>
										<area BETYPE="IDREF" FILEID="ALTO00005" BEGIN="P5_TB00003"/>
									</fptr>
								</div>
							</div>
							<div ID="L.1.1.6.2.1.2" TYPE="Paragraph" ORDER="2">
								<div ID="L.1.1.6.2.1.2.1" TYPE="Text">
									<fptr>
										<area BETYPE="IDREF" FILEID="ALTO00005" BEGIN="P5_TB00004"/>
									</fptr>
								</div>
							</div>
							<div ID="L.1.1.6.2.1.3" TYPE="Paragraph" ORDER="3">
								<div ID="L.1.1.6.2.1.3.1" TYPE="Text">
									<fptr>
										<area BETYPE="IDREF" FILEID="ALTO00005" BEGIN="P5_TB00005"/>
									</fptr>
								</div>
							</div>
						</div>
					</div>
				</div>
				<div ID="L.1.1.7" TYPE="TextContent" ORDER="7" DMDID="c006" LABEL="Činnost našich spolkův a ruch náš hudební.">
					<div ID="L.1.1.7.1" TYPE="Head">
						<fptr>
							<area BETYPE="IDREF" FILEID="ALTO00005" BEGIN="P5_TB00006"/>
						</fptr>
					</div>
					<div ID="L.1.1.7.2" TYPE="Copy">
						<div ID="L.1.1.7.2.1" TYPE="BodyContent">
							<div ID="L.1.1.7.2.1.1" TYPE="Paragraph" ORDER="1">
								<div ID="L.1.1.7.2.1.1.1" TYPE="Text">
									<fptr>
										<area BETYPE="IDREF" FILEID="ALTO00005" BEGIN="P5_TB00007"/>
									</fptr>
								</div>
							</div>
							<div ID="L.1.1.7.2.1.2" TYPE="Paragraph" ORDER="2">
								<div ID="L.1.1.7.2.1.2.1" TYPE="Text">
									<fptr>
										<area BETYPE="IDREF" FILEID="ALTO00006" BEGIN="P6_TB00001"/>
									</fptr>
								</div>
							</div>
							<div ID="L.1.1.7.2.1.3" TYPE="Paragraph" ORDER="3">
								<div ID="L.1.1.7.2.1.3.1" TYPE="Text">
									<fptr>
										<area BETYPE="IDREF" FILEID="ALTO00006" BEGIN="P6_TB00002"/>
									</fptr>
								</div>
							</div>
							<div ID="L.1.1.7.2.1.4" TYPE="Paragraph" ORDER="4">
								<div ID="L.1.1.7.2.1.4.1" TYPE="Text">
									<fptr>
										<area BETYPE="IDREF" FILEID="ALTO00007" BEGIN="P7_TB00001"/>
									</fptr>
								</div>
							</div>
							<div ID="L.1.1.7.2.1.5" TYPE="Paragraph" ORDER="5">
								<div ID="L.1.1.7.2.1.5.1" TYPE="Text">
									<fptr>
										<area BETYPE="IDREF" FILEID="ALTO00007" BEGIN="P7_TB00002"/>
									</fptr>
								</div>
							</div>
							<div ID="L.1.1.7.2.1.6" TYPE="Paragraph" ORDER="6">
								<div ID="L.1.1.7.2.1.6.1" TYPE="Text">
									<fptr>
										<area BETYPE="IDREF" FILEID="ALTO00008" BEGIN="P8_TB00001"/>
									</fptr>
								</div>
							</div>
						</div>
						<div ID="L.1.1.7.2.2" TYPE="Footnote">
							<div ID="L.1.1.7.2.2.1" TYPE="Text">
								<fptr>
									<area BETYPE="IDREF" FILEID="ALTO00006" BEGIN="P6_TB00003"/>
								</fptr>
							</div>
						</div>
						<div ID="L.1.1.7.2.3" TYPE="Footnote">
							<div ID="L.1.1.7.2.3.1" TYPE="Text">
								<fptr>
									<area BETYPE="IDREF" FILEID="ALTO00006" BEGIN="P6_TB00004"/>
								</fptr>
							</div>
						</div>
						<div ID="L.1.1.7.2.4" TYPE="Footnote">
							<div ID="L.1.1.7.2.4.1" TYPE="Text">
								<fptr>
									<area BETYPE="IDREF" FILEID="ALTO00007" BEGIN="P7_TB00003"/>
								</fptr>
							</div>
						</div>
					</div>
				</div>
				<div ID="L.1.1.8" TYPE="TextContent" ORDER="8" DMDID="c007" LABEL="ÚMRTÍ.">
					<div ID="L.1.1.8.1" TYPE="Head">
						<fptr>
							<area BETYPE="IDREF" FILEID="ALTO00008" BEGIN="P8_TB00002"/>
						</fptr>
					</div>
					<div ID="L.1.1.8.2" TYPE="Copy">
						<div ID="L.1.1.8.2.1" TYPE="BodyContent">
							<div ID="L.1.1.8.2.1.1" TYPE="Paragraph" ORDER="1">
								<div ID="L.1.1.8.2.1.1.1" TYPE="Text">
									<fptr>
										<area BETYPE="IDREF" FILEID="ALTO00008" BEGIN="P8_TB00003"/>
									</fptr>
								</div>
							</div>
							<div ID="L.1.1.8.2.1.2" TYPE="Paragraph" ORDER="2">
								<div ID="L.1.1.8.2.1.2.1" TYPE="Text">
									<fptr>
										<area BETYPE="IDREF" FILEID="ALTO00008" BEGIN="P8_TB00004"/>
									</fptr>
								</div>
							</div>
						</div>
					</div>
				</div>
				<div ID="L.1.1.9" TYPE="TextContent" ORDER="9" DMDID="c008" LABEL="RŮZNÉ ZPRÁVY.">
					<div ID="L.1.1.9.1" TYPE="Head">
						<fptr>
							<area BETYPE="IDREF" FILEID="ALTO00008" BEGIN="P8_TB00005"/>
						</fptr>
					</div>
					<div ID="L.1.1.9.2" TYPE="Copy">
						<div ID="L.1.1.9.2.1" TYPE="BodyContent">
							<div ID="L.1.1.9.2.1.1" TYPE="Paragraph" ORDER="1">
								<div ID="L.1.1.9.2.1.1.1" TYPE="Text">
									<fptr>
										<area BETYPE="IDREF" FILEID="ALTO00008" BEGIN="P8_TB00006"/>
									</fptr>
								</div>
							</div>
							<div ID="L.1.1.9.2.1.2" TYPE="Paragraph" ORDER="2">
								<div ID="L.1.1.9.2.1.2.1" TYPE="Text">
									<fptr>
										<area BETYPE="IDREF" FILEID="ALTO00009" BEGIN="P9_TB00001"/>
									</fptr>
								</div>
							</div>
							<div ID="L.1.1.9.2.1.3" TYPE="Paragraph" ORDER="3">
								<div ID="L.1.1.9.2.1.3.1" TYPE="Text">
									<fptr>
										<area BETYPE="IDREF" FILEID="ALTO00009" BEGIN="P9_TB00002"/>
									</fptr>
								</div>
							</div>
							<div ID="L.1.1.9.2.1.4" TYPE="Paragraph" ORDER="4">
								<div ID="L.1.1.9.2.1.4.1" TYPE="Text">
									<fptr>
										<area BETYPE="IDREF" FILEID="ALTO00010" BEGIN="P10_TB00001"/>
									</fptr>
								</div>
							</div>
							<div ID="L.1.1.9.2.1.5" TYPE="Paragraph" ORDER="5">
								<div ID="L.1.1.9.2.1.5.1" TYPE="Text">
									<fptr>
										<area BETYPE="IDREF" FILEID="ALTO00010" BEGIN="P10_TB00002"/>
									</fptr>
								</div>
							</div>
							<div ID="L.1.1.9.2.1.6" TYPE="Paragraph" ORDER="6">
								<div ID="L.1.1.9.2.1.6.1" TYPE="Text">
									<fptr>
										<seq>
											<area BETYPE="IDREF" FILEID="ALTO00010" BEGIN="P10_TB00003"/>
											<area BETYPE="IDREF" FILEID="ALTO00011" BEGIN="P11_TB00002"/>
										</seq>
									</fptr>
								</div>
							</div>
						</div>
					</div>
				</div>
				<div ID="L.1.1.10" TYPE="TextContent" ORDER="10" DMDID="c009" LABEL="SMĚS.">
					<div ID="L.1.1.10.1" TYPE="Head">
						<fptr>
							<area BETYPE="IDREF" FILEID="ALTO00011" BEGIN="P11_TB00003"/>
						</fptr>
					</div>
					<div ID="L.1.1.10.2" TYPE="HeadingText">
						<div ID="L.1.1.10.2.1" TYPE="Text">
							<fptr>
								<area BETYPE="IDREF" FILEID="ALTO00011" BEGIN="P11_TB00004"/>
							</fptr>
						</div>
					</div>
				</div>
				<div ID="L.1.1.11" TYPE="TextContent" ORDER="11" DMDID="c010" LABEL="Listárna redakce.">
					<div ID="L.1.1.11.1" TYPE="Head">
						<fptr>
							<area BETYPE="IDREF" FILEID="ALTO00011" BEGIN="P11_TB00005"/>
						</fptr>
					</div>
					<div ID="L.1.1.11.2" TYPE="Copy">
						<div ID="L.1.1.11.2.1" TYPE="BodyContent">
							<div ID="L.1.1.11.2.1.1" TYPE="Paragraph" ORDER="1">
								<div ID="L.1.1.11.2.1.1.1" TYPE="Text">
									<fptr>
										<area BETYPE="IDREF" FILEID="ALTO00011" BEGIN="P11_TB00006"/>
									</fptr>
								</div>
							</div>
						</div>
					</div>
				</div>
				<div ID="L.1.1.12" TYPE="SponsoredAdvertisement" LABEL="Sponsored Advertisements">
					<div ID="L.1.1.12.1" TYPE="SponsoredAd" DMDID="c011">
						<fptr>
							<area BETYPE="IDREF" FILEID="ALTO00011" BEGIN="P11_CB00001"/>
						</fptr>
					</div>
					<div ID="L.1.1.12.2" TYPE="SponsoredAd" DMDID="c012">
						<fptr>
							<area BETYPE="IDREF" FILEID="ALTO00012" BEGIN="P12_CB00001"/>
						</fptr>
					</div>
					<div ID="L.1.1.12.3" TYPE="SponsoredAd" DMDID="c013">
						<fptr>
							<area BETYPE="IDREF" FILEID="ALTO00012" BEGIN="P12_CB00002"/>
						</fptr>
					</div>
				</div>
			</div>
		</div>
	</structMap>
</mets>
